[
    {
        "id": "eth",
        "logo": "https://s2.coinmarketcap.com/static/img/coins/32x32/1027.png",
        "name": "ETH",
        "symbol": "ETH",
        "networks": [
            "eth",
            "polygon",
            "loopring",
            "xdai",
            "zksync",
            "hermez"
        ],
        "active": true
    },
    {
        "id": "dai",
        "logo": "https://s2.coinmarketcap.com/static/img/coins/32x32/4943.png",
        "name": "DAI",
        "symbol": "DAI",
        "networks": [
            "eth",
            "polygon",
            "loopring",
            "xdai",
            "zksync",
            "hermez"
        ],
        "active": true
    },
    {
        "id": "usdt",
        "logo": "https://s2.coinmarketcap.com/static/img/coins/32x32/825.png",
        "name": "USDT",
        "symbol": "USDT",
        "networks": [
            "eth",
            "polygon"
        ],
        "active": true
    },
    {
        "id": "usdc",
        "cmcId": "https://s2.coinmarketcap.com/static/img/coins/32x32/3408.png",
        "name": "USDC",
        "symbol": "USDC",
        "networks": [
            "eth"
        ],
        "active": true
    },
    {
        "id": "czk",
        "logo": "https://firebasestorage.googleapis.com/v0/b/gwei-p2p.appspot.com/o/currencies%2Fczk.png?alt=media",
        "name": "Česká koruna",
        "symbol": "Kč",
        "networks": [
            "revolut",
            "paypal"
        ],
        "active": true
    }
]
